{
  "singulars": {
    "body": {
      "contact": "Medijsko in poslovno povpraševanje se lahko pošlje na <0>contact@walkscape.app</0>",
      "description": "Če imaš kakšno vprašanje ali potrebuješ pomoč, nas lahko kontaktiraš preko e-pošte <0>contact@walkscape.app</0> ali socialnih omrežij.",
      "support": "Če imaš težave z igro, računom ali s postopkom naročnine, nas brez težav kontaktiraj preko e-pošte <0>support@walkscape.app</0> ali preko socialnih medijev."
    },
    "meta": {
      "description": "Preveri, kako nas lahko kontaktiraš",
      "title": "WalkScape | Kontaktiraj nas"
    },
    "presskit": {
      "description": "Poglej si naš celoten promocijski material <0>tukaj</0>",
      "title": "Promocijski material"
    },
    "title": "Kontaktiraj nas"
  }
}
